mcp_requests/__init__.py
mcp_requests/main.py
mcp_request-0.1.3.dist-info/METADATA
mcp_request-0.1.3.dist-info/WHEEL
mcp_request-0.1.3.dist-info/entry_points.txt
mcp_request-0.1.3.dist-info/licenses/LICENSE
mcp_request-0.1.3.dist-info/RECORD
