Metadata-Version: 2.4
Name: mcp-request
Version: 0.1.3
Summary: A comprehensive HTTP client MCP server for security testing, API testing, and web automation
Project-URL: Homepage, https://github.com/godzeo/mcp-request
Project-URL: Bug Reports, https://github.com/godzeo/mcp-request/issues
Project-URL: Source, https://github.com/godzeo/mcp-request
Author-email: Zeo <zzzhhhaaaiiii@gmail.com>
License: MIT
License-File: LICENSE
Keywords: api-testing,curl,http,httpx,mcp,penetration-testing,security-testing
Classifier: Development Status :: 4 - Beta
Classifier: Intended Audience :: Developers
Classifier: Intended Audience :: Information Technology
Classifier: License :: OSI Approved :: MIT License
Classifier: Operating System :: OS Independent
Classifier: Programming Language :: Python :: 3
Classifier: Programming Language :: Python :: 3.13
Classifier: Topic :: Internet :: WWW/HTTP :: HTTP Servers
Classifier: Topic :: Security
Classifier: Topic :: Software Development :: Testing
Classifier: Topic :: System :: Networking
Requires-Python: >=3.13
Requires-Dist: build>=1.2.2.post1
Requires-Dist: httpx>=0.25.0
Requires-Dist: mcp[cli]>=1.9.4
Requires-Dist: pydantic>=2.0.0
Requires-Dist: twine>=6.1.0
